pycociC/__init__.py
pycociC/__main__.py
pycociC-1.1.2.dist-info/LICENSE
pycociC-1.1.2.dist-info/METADATA
pycociC-1.1.2.dist-info/WHEEL
pycociC-1.1.2.dist-info/top_level.txt
pycociC-1.1.2.dist-info/RECORD
